{"effect_chance":null,"generation":{"url":"https:\/\/pokeapi.co\/api\/v2\/generation\/1\/","name":"generation-i"},"stat_changes":[{"stat":{"url":"https:\/\/pokeapi.co\/api\/v2\/stat\/5\/","name":"special-defense"},"change":2}],"effect_changes":[],"names":[{"name":"\u77ac\u95f4\u5931\u5fc6","language":{"url":"https:\/\/pokeapi.co\/api\/v2\/language\/12\/","name":"zh-Hans"}},{"name":"\u30c9\u308f\u3059\u308c","language":{"url":"https:\/\/pokeapi.co\/api\/v2\/language\/11\/","name":"ja"}},{"name":"Amnesia","language":{"url":"https:\/\/pokeapi.co\/api\/v2\/language\/9\/","name":"en"}},{"name":"Amnesia","language":{"url":"https:\/\/pokeapi.co\/api\/v2\/language\/8\/","name":"it"}},{"name":"Amnesia","language":{"url":"https:\/\/pokeapi.co\/api\/v2\/language\/7\/","name":"es"}},{"name":"Amnesie","language":{"url":"https:\/\/pokeapi.co\/api\/v2\/language\/6\/","name":"de"}},{"name":"Amn\u00e9sie","language":{"url":"https:\/\/pokeapi.co\/api\/v2\/language\/5\/","name":"fr"}},{"name":"\u77ac\u9593\u5931\u61b6","language":{"url":"https:\/\/pokeapi.co\/api\/v2\/language\/4\/","name":"zh-Hant"}},{"name":"\ub9dd\uac01\uc220","language":{"url":"https:\/\/pokeapi.co\/api\/v2\/language\/3\/","name":"ko"}},{"name":"\u30c9\u308f\u3059\u308c","language":{"url":"https:\/\/pokeapi.co\/api\/v2\/language\/1\/","name":"ja-Hrkt"}}],"id":133,"machines":[],"pp":20,"contest_combos":null,"effect_entries":[{"short_effect":"Raises the user's Special Defense by two stages.","effect":"Raises the user's Special Defense by two stages.","language":{"url":"https:\/\/pokeapi.co\/api\/v2\/language\/9\/","name":"en"}}],"contest_type":{"url":"https:\/\/pokeapi.co\/api\/v2\/contest-type\/3\/","name":"cute"},"priority":0,"contest_effect":{"url":"https:\/\/pokeapi.co\/api\/v2\/contest-effect\/32\/"},"type":{"url":"https:\/\/pokeapi.co\/api\/v2\/type\/14\/","name":"psychic"},"accuracy":null,"power":null,"past_values":[],"target":{"url":"https:\/\/pokeapi.co\/api\/v2\/move-target\/7\/","name":"user"},"super_contest_effect":{"url":"https:\/\/pokeapi.co\/api\/v2\/super-contest-effect\/11\/"},"name":"amnesia","flavor_text_entries":[{"flavor_text":"\u5c06\u5934\u8111\u6e05\u7a7a\uff0c\n\u77ac\u95f4\u5fd8\u8bb0\u67d0\u4e8b\uff0c\n\u4ece\u800c\u5927\u5e45\u63d0\u9ad8\u81ea\u5df1\u7684\u7279\u9632\u3002","language":{"url":"https:\/\/pokeapi.co\/api\/v2\/language\/12\/","name":"zh-Hans"},"version_group":{"url":"https:\/\/pokeapi.co\/api\/v2\/version-group\/17\/","name":"sun-moon"}},{"flavor_text":"\u982d\u3092\u3000\u304b\u3089\u306b\u3057\u3066\n\u4e00\u77ac\u3000\u306a\u306b\u304b\u3092\u3000\u5fd8\u308c\u308b\u3053\u3068\u3067\n\u81ea\u5206\u306e\u3000\u7279\u9632\u3092\u3000\u3050\u30fc\u3093\u3068\u3000\u3042\u3052\u308b\u3002","language":{"url":"https:\/\/pokeapi.co\/api\/v2\/language\/11\/","name":"ja"},"version_group":{"url":"https:\/\/pokeapi.co\/api\/v2\/version-group\/17\/","name":"sun-moon"}},{"flavor_text":"The user temporarily empties its mind to forget its\nconcerns. This sharply raises the user\u2019s Sp. Def stat.","language":{"url":"https:\/\/pokeapi.co\/api\/v2\/language\/9\/","name":"en"},"version_group":{"url":"https:\/\/pokeapi.co\/api\/v2\/version-group\/17\/","name":"sun-moon"}},{"flavor_text":"Chi la usa svuota per un po\u2019 la mente per\ndimenticare i problemi. La Difesa Speciale\naumenta di molto.","language":{"url":"https:\/\/pokeapi.co\/api\/v2\/language\/8\/","name":"it"},"version_group":{"url":"https:\/\/pokeapi.co\/api\/v2\/version-group\/17\/","name":"sun-moon"}},{"flavor_text":"El usuario olvida sus preocupaciones y aumenta \nmucho la Defensa Especial.","language":{"url":"https:\/\/pokeapi.co\/api\/v2\/language\/7\/","name":"es"},"version_group":{"url":"https:\/\/pokeapi.co\/api\/v2\/version-group\/17\/","name":"sun-moon"}},{"flavor_text":"Ged\u00e4chtnisverlust, der die Spezial-Verteidigung\nstark erh\u00f6ht.","language":{"url":"https:\/\/pokeapi.co\/api\/v2\/language\/6\/","name":"de"},"version_group":{"url":"https:\/\/pokeapi.co\/api\/v2\/version-group\/17\/","name":"sun-moon"}},{"flavor_text":"Le lanceur fait le vide dans son esprit pour\noublier ses soucis. Augmente beaucoup sa\nD\u00e9fense Sp\u00e9ciale.","language":{"url":"https:\/\/pokeapi.co\/api\/v2\/language\/5\/","name":"fr"},"version_group":{"url":"https:\/\/pokeapi.co\/api\/v2\/version-group\/17\/","name":"sun-moon"}},{"flavor_text":"\u5c07\u982d\u8166\u6e05\u7a7a\uff0c\n\u85c9\u7531\u5728\u4e00\u77ac\u9593\u907a\u5fd8\u67d0\u4e9b\u4e8b\n\u5927\u5e45\u63d0\u9ad8\u81ea\u5df1\u7684\u7279\u9632\u3002","language":{"url":"https:\/\/pokeapi.co\/api\/v2\/language\/4\/","name":"zh-Hant"},"version_group":{"url":"https:\/\/pokeapi.co\/api\/v2\/version-group\/17\/","name":"sun-moon"}},{"flavor_text":"\uba38\ub9ac\ub97c \ube44\uc6cc\uc11c \uc21c\uac04\uc801\uc73c\ub85c\n\ubb34\uc5b8\uac00\ub97c \uc78a\uc5b4\ubc84\ub9bc\uc73c\ub85c\uc368\n\uc790\uc2e0\uc758 \ud2b9\uc218\ubc29\uc5b4\ub97c \ud06c\uac8c \uc62c\ub9b0\ub2e4.","language":{"url":"https:\/\/pokeapi.co\/api\/v2\/language\/3\/","name":"ko"},"version_group":{"url":"https:\/\/pokeapi.co\/api\/v2\/version-group\/17\/","name":"sun-moon"}},{"flavor_text":"\u3042\u305f\u307e\u3092\u3000\u304b\u3089\u306b\u3057\u3066\n\u3044\u3063\u3057\u3085\u3093\u3000\u306a\u306b\u304b\u3092\u3000\u308f\u3059\u308c\u308b\u3000\u3053\u3068\u3067\n\u3058\u3076\u3093\u306e\u3000\u3068\u304f\u307c\u3046\u3092\u3000\u3050\u30fc\u3093\u3068\u3000\u3042\u3052\u308b\u3002","language":{"url":"https:\/\/pokeapi.co\/api\/v2\/language\/1\/","name":"ja-Hrkt"},"version_group":{"url":"https:\/\/pokeapi.co\/api\/v2\/version-group\/17\/","name":"sun-moon"}},{"flavor_text":"\u982d\u3092\u3000\u304b\u3089\u306b\u3057\u3066\n\u4e00\u77ac\u3000\u306a\u306b\u304b\u3092\u3000\u5fd8\u308c\u308b\u3053\u3068\u3067\n\u81ea\u5206\u306e\u3000\u7279\u9632\u3092\u3000\u3050\u30fc\u3093\u3068\u3000\u3042\u3052\u308b\u3002","language":{"url":"https:\/\/pokeapi.co\/api\/v2\/language\/11\/","name":"ja"},"version_group":{"url":"https:\/\/pokeapi.co\/api\/v2\/version-group\/16\/","name":"omega-ruby-alpha-sapphire"}},{"flavor_text":"The user temporarily empties its mind to\nforget its concerns.\nThis sharply raises the user\u2019s Sp. Def stat.","language":{"url":"https:\/\/pokeapi.co\/api\/v2\/language\/9\/","name":"en"},"version_group":{"url":"https:\/\/pokeapi.co\/api\/v2\/version-group\/16\/","name":"omega-ruby-alpha-sapphire"}},{"flavor_text":"Chi la usa svuota per un po\u2019 la mente per\ndimenticare i problemi. La Difesa Speciale\naumenta di molto.","language":{"url":"https:\/\/pokeapi.co\/api\/v2\/language\/8\/","name":"it"},"version_group":{"url":"https:\/\/pokeapi.co\/api\/v2\/version-group\/16\/","name":"omega-ruby-alpha-sapphire"}},{"flavor_text":"El usuario olvida sus preocupaciones y aumenta \nmucho la Defensa Especial.","language":{"url":"https:\/\/pokeapi.co\/api\/v2\/language\/7\/","name":"es"},"version_group":{"url":"https:\/\/pokeapi.co\/api\/v2\/version-group\/16\/","name":"omega-ruby-alpha-sapphire"}},{"flavor_text":"Ged\u00e4chtnisverlust, der die Spezial-Verteidigung\nstark erh\u00f6ht.","language":{"url":"https:\/\/pokeapi.co\/api\/v2\/language\/6\/","name":"de"},"version_group":{"url":"https:\/\/pokeapi.co\/api\/v2\/version-group\/16\/","name":"omega-ruby-alpha-sapphire"}},{"flavor_text":"Le lanceur fait le vide dans son esprit pour\noublier ses soucis. Augmente fortement sa\nD\u00e9fense Sp\u00e9ciale.","language":{"url":"https:\/\/pokeapi.co\/api\/v2\/language\/5\/","name":"fr"},"version_group":{"url":"https:\/\/pokeapi.co\/api\/v2\/version-group\/16\/","name":"omega-ruby-alpha-sapphire"}},{"flavor_text":"\uba38\ub9ac\ub97c \ube44\uc6cc\uc11c \uc21c\uac04\uc801\uc73c\ub85c\n\ubb34\uc5b8\uac00\ub97c \uc78a\uc5b4\ubc84\ub9bc\uc73c\ub85c\uc368\n\uc790\uc2e0\uc758 \ud2b9\uc218\ubc29\uc5b4\ub97c \ud06c\uac8c \uc62c\ub9b0\ub2e4.","language":{"url":"https:\/\/pokeapi.co\/api\/v2\/language\/3\/","name":"ko"},"version_group":{"url":"https:\/\/pokeapi.co\/api\/v2\/version-group\/16\/","name":"omega-ruby-alpha-sapphire"}},{"flavor_text":"\u3042\u305f\u307e\u3092\u3000\u304b\u3089\u306b\u3057\u3066\n\u3044\u3063\u3057\u3085\u3093\u3000\u306a\u306b\u304b\u3092\u3000\u308f\u3059\u308c\u308b\u3000\u3053\u3068\u3067\n\u3058\u3076\u3093\u306e\u3000\u3068\u304f\u307c\u3046\u3092\u3000\u3050\u30fc\u3093\u3068\u3000\u3042\u3052\u308b\u3002","language":{"url":"https:\/\/pokeapi.co\/api\/v2\/language\/1\/","name":"ja-Hrkt"},"version_group":{"url":"https:\/\/pokeapi.co\/api\/v2\/version-group\/16\/","name":"omega-ruby-alpha-sapphire"}},{"flavor_text":"\u982d\u3092\u3000\u304b\u3089\u306b\u3057\u3066\n\u4e00\u77ac\u3000\u306a\u306b\u304b\u3092\u3000\u5fd8\u308c\u308b\u3053\u3068\u3067\n\u81ea\u5206\u306e\u3000\u7279\u9632\u3092\u3000\u3050\u30fc\u3093\u3068\u3000\u3042\u3052\u308b\u3002","language":{"url":"https:\/\/pokeapi.co\/api\/v2\/language\/11\/","name":"ja"},"version_group":{"url":"https:\/\/pokeapi.co\/api\/v2\/version-group\/15\/","name":"x-y"}},{"flavor_text":"The user temporarily empties its mind to\nforget its concerns.\nThis sharply raises the user\u2019s Sp. Def stat.","language":{"url":"https:\/\/pokeapi.co\/api\/v2\/language\/9\/","name":"en"},"version_group":{"url":"https:\/\/pokeapi.co\/api\/v2\/version-group\/15\/","name":"x-y"}},{"flavor_text":"Chi la usa svuota per un po\u2019 la mente per\ndimenticare i problemi. La Difesa Speciale\naumenta di molto.","language":{"url":"https:\/\/pokeapi.co\/api\/v2\/language\/8\/","name":"it"},"version_group":{"url":"https:\/\/pokeapi.co\/api\/v2\/version-group\/15\/","name":"x-y"}},{"flavor_text":"El usuario olvida sus preocupaciones y aumenta\nmucho la Defensa Especial.","language":{"url":"https:\/\/pokeapi.co\/api\/v2\/language\/7\/","name":"es"},"version_group":{"url":"https:\/\/pokeapi.co\/api\/v2\/version-group\/15\/","name":"x-y"}},{"flavor_text":"Ged\u00e4chtnisverlust, der die Spezial-Verteidigung\nstark erh\u00f6ht.","language":{"url":"https:\/\/pokeapi.co\/api\/v2\/language\/6\/","name":"de"},"version_group":{"url":"https:\/\/pokeapi.co\/api\/v2\/version-group\/15\/","name":"x-y"}},{"flavor_text":"Le lanceur fait le vide dans son esprit pour\noublier ses soucis. Augmente fortement sa\nD\u00e9fense Sp\u00e9ciale.","language":{"url":"https:\/\/pokeapi.co\/api\/v2\/language\/5\/","name":"fr"},"version_group":{"url":"https:\/\/pokeapi.co\/api\/v2\/version-group\/15\/","name":"x-y"}},{"flavor_text":"\uba38\ub9ac\ub97c \ube44\uc6cc\uc11c \uc21c\uac04\uc801\uc73c\ub85c\n\ubb34\uc5b8\uac00\ub97c \uc78a\uc5b4\ubc84\ub9bc\uc73c\ub85c\uc368\n\uc790\uc2e0\uc758 \ud2b9\uc218\ubc29\uc5b4\ub97c \ud06c\uac8c \uc62c\ub9b0\ub2e4.","language":{"url":"https:\/\/pokeapi.co\/api\/v2\/language\/3\/","name":"ko"},"version_group":{"url":"https:\/\/pokeapi.co\/api\/v2\/version-group\/15\/","name":"x-y"}},{"flavor_text":"\u3042\u305f\u307e\u3092\u3000\u304b\u3089\u306b\u3057\u3066\n\u3044\u3063\u3057\u3085\u3093\u3000\u306a\u306b\u304b\u3092\u3000\u308f\u3059\u308c\u308b\u3000\u3053\u3068\u3067\n\u3058\u3076\u3093\u306e\u3000\u3068\u304f\u307c\u3046\u3092\u3000\u3050\u30fc\u3093\u3068\u3000\u3042\u3052\u308b\u3002","language":{"url":"https:\/\/pokeapi.co\/api\/v2\/language\/1\/","name":"ja-Hrkt"},"version_group":{"url":"https:\/\/pokeapi.co\/api\/v2\/version-group\/15\/","name":"x-y"}},{"flavor_text":"The user temporarily empties its mind to\nforget its concerns.\nIt sharply raises the user\u2019s Sp. Def stat.","language":{"url":"https:\/\/pokeapi.co\/api\/v2\/language\/9\/","name":"en"},"version_group":{"url":"https:\/\/pokeapi.co\/api\/v2\/version-group\/14\/","name":"black-2-white-2"}},{"flavor_text":"The user temporarily empties its mind to\nforget its concerns.\nIt sharply raises the user\u2019s Sp. Def stat.","language":{"url":"https:\/\/pokeapi.co\/api\/v2\/language\/9\/","name":"en"},"version_group":{"url":"https:\/\/pokeapi.co\/api\/v2\/version-group\/11\/","name":"black-white"}},{"flavor_text":"Le lanceur fait le vide dans son esprit\npour oublier ses soucis. Augmente\nfortement sa D\u00e9fense Sp\u00e9ciale.","language":{"url":"https:\/\/pokeapi.co\/api\/v2\/language\/5\/","name":"fr"},"version_group":{"url":"https:\/\/pokeapi.co\/api\/v2\/version-group\/11\/","name":"black-white"}},{"flavor_text":"The user temporarily\nempties its mind to\nforget its concerns.\nIt sharply raises the\nuser\u2019s Sp. Def stat.","language":{"url":"https:\/\/pokeapi.co\/api\/v2\/language\/9\/","name":"en"},"version_group":{"url":"https:\/\/pokeapi.co\/api\/v2\/version-group\/10\/","name":"heartgold-soulsilver"}},{"flavor_text":"The user temporarily\nempties its mind to\nforget its concerns.\nIt sharply raises the\nuser\u2019s Sp. Def stat.","language":{"url":"https:\/\/pokeapi.co\/api\/v2\/language\/9\/","name":"en"},"version_group":{"url":"https:\/\/pokeapi.co\/api\/v2\/version-group\/9\/","name":"platinum"}},{"flavor_text":"The user temporarily\nempties its mind to\nforget its concerns.\nIt sharply raises the\nuser\u2019s Sp. Def stat.","language":{"url":"https:\/\/pokeapi.co\/api\/v2\/language\/9\/","name":"en"},"version_group":{"url":"https:\/\/pokeapi.co\/api\/v2\/version-group\/8\/","name":"diamond-pearl"}},{"flavor_text":"Forgets about\nsomething and\nsharply raises\nSP. DEF.","language":{"url":"https:\/\/pokeapi.co\/api\/v2\/language\/9\/","name":"en"},"version_group":{"url":"https:\/\/pokeapi.co\/api\/v2\/version-group\/7\/","name":"firered-leafgreen"}},{"flavor_text":"Forgets about something\nand sharply raises SP. DEF.","language":{"url":"https:\/\/pokeapi.co\/api\/v2\/language\/9\/","name":"en"},"version_group":{"url":"https:\/\/pokeapi.co\/api\/v2\/version-group\/6\/","name":"emerald"}},{"flavor_text":"Forgets about something\nand sharply raises SP. DEF.","language":{"url":"https:\/\/pokeapi.co\/api\/v2\/language\/9\/","name":"en"},"version_group":{"url":"https:\/\/pokeapi.co\/api\/v2\/version-group\/5\/","name":"ruby-sapphire"}},{"flavor_text":"Sharply raises the\nuser's SPCL.DEF.","language":{"url":"https:\/\/pokeapi.co\/api\/v2\/language\/9\/","name":"en"},"version_group":{"url":"https:\/\/pokeapi.co\/api\/v2\/version-group\/4\/","name":"crystal"}},{"flavor_text":"Sharply raises the\nuser's SPCL.DEF.","language":{"url":"https:\/\/pokeapi.co\/api\/v2\/language\/9\/","name":"en"},"version_group":{"url":"https:\/\/pokeapi.co\/api\/v2\/version-group\/3\/","name":"gold-silver"}}],"damage_class":{"url":"https:\/\/pokeapi.co\/api\/v2\/move-damage-class\/1\/","name":"status"},"meta":{"category":{"url":"https:\/\/pokeapi.co\/api\/v2\/move-category\/2\/","name":"net-good-stats"},"healing":0,"max_turns":null,"drain":0,"ailment":{"url":"https:\/\/pokeapi.co\/api\/v2\/move-ailment\/0\/","name":"none"},"stat_chance":0,"flinch_chance":0,"min_hits":null,"ailment_chance":0,"crit_rate":0,"min_turns":null,"max_hits":null}}